SBTi/.DS_Store
SBTi/__init__.py
SBTi/configs.py
SBTi/data/__init__.py
SBTi/data/bloomberg.py
SBTi/data/cdp.py
SBTi/data/csv.py
SBTi/data/data_provider.py
SBTi/data/excel.py
SBTi/data/iss.py
SBTi/data/msci.py
SBTi/data/sbti.py
SBTi/data/trucost.py
SBTi/data/urgentem.py
SBTi/inputs/current-Companies-Taking-Action.xlsx
SBTi/inputs/regression_model_summary.xlsx
SBTi/inputs/sr15_mapping.xlsx
SBTi/interfaces.py
SBTi/portfolio_aggregation.py
SBTi/portfolio_coverage_tvp.py
SBTi/target_validation.py
SBTi/temperature_score.py
SBTi/utils.py
sbti_finance_tool-1.1.2.dist-info/LICENSE
sbti_finance_tool-1.1.2.dist-info/METADATA
sbti_finance_tool-1.1.2.dist-info/WHEEL
sbti_finance_tool-1.1.2.dist-info/RECORD
