Metadata-Version: 2.3
Name: sbti-finance-tool
Version: 1.1.2
Summary: This package helps companies and financial institutions to assess the temperature alignment of current targets, commitments, and investment and lending portfolios, and to use this information to develop targets for official validation by the SBTi.'
License: MIT
Keywords: Climate,SBTi,Finance
Author: sbti
Author-email: financialinstitutions@sciencebasedtargets.org
Requires-Python: >=3.9,<4.0
Classifier: Intended Audience :: Developers
Classifier: Intended Audience :: Science/Research
Classifier: License :: OSI Approved :: MIT License
Classifier: Operating System :: MacOS
Classifier: Operating System :: Microsoft :: Windows
Classifier: Operating System :: Unix
Classifier: Programming Language :: Python
Classifier: Programming Language :: Python :: 3
Classifier: Programming Language :: Python :: 3.9
Classifier: Programming Language :: Python :: 3.10
Classifier: Programming Language :: Python :: 3.11
Classifier: Programming Language :: Python :: 3.12
Classifier: Programming Language :: Python :: 3.13
Classifier: Programming Language :: Python :: 3 :: Only
Classifier: Programming Language :: Python :: 3.8
Classifier: Topic :: Scientific/Engineering
Classifier: Topic :: Software Development
Requires-Dist: cleo (>=2.0.1,<3.0.0)
Requires-Dist: numpy (>=1.21.0,<2.0.0)
Requires-Dist: openpyxl (==3.1.2)
Requires-Dist: pandas (==1.5.3)
Requires-Dist: pydantic (==1.10.7)
Requires-Dist: requests (==2.31.0)
Requires-Dist: six (==1.16.0)
Requires-Dist: xlrd (==2.0.1)
Project-URL: Bug Tracker, https://github.com/ScienceBasedTargets/SBTi-finance-tool/issues
Project-URL: Documentation, https://sciencebasedtargets.github.io/SBTi-finance-tool
Project-URL: Source Code, https://github.com/ScienceBasedTargets/SBTi-finance-tool
